house_prices/__init__.py
house_prices/inference.py
house_prices/preprocess.py
house_prices/train.py
house_epita_dsp_prices_0.3.0-0.3.0.dist-info/METADATA
house_epita_dsp_prices_0.3.0-0.3.0.dist-info/WHEEL
house_epita_dsp_prices_0.3.0-0.3.0.dist-info/top_level.txt
house_epita_dsp_prices_0.3.0-0.3.0.dist-info/RECORD
