Metadata-Version: 2.1
Name: house-epita-dsp-prices-0.3.0
Version: 0.3.0
Summary: A package for creating house prices predictions
Home-page: https://github.com/callmeeric5/dsp-zihang-wang
Author: Eric Windsor
Author-email: zihang.wang@epita.fr
License: BSD 2-clause
Classifier: Development Status :: 5 - Production/Stable
Classifier: Intended Audience :: Science/Research
Classifier: License :: OSI Approved :: BSD License
Classifier: Operating System :: POSIX :: Linux
Classifier: Programming Language :: Python :: 2
Classifier: Programming Language :: Python :: 2.7
Classifier: Programming Language :: Python :: 3
Classifier: Programming Language :: Python :: 3.4
Classifier: Programming Language :: Python :: 3.5
Requires-Dist: house-prices ==0.1.0
Requires-Dist: joblib ==1.2.0
Requires-Dist: matplotlib ==3.8.0
Requires-Dist: numpy ==1.26.4
Requires-Dist: pandas ==2.2.1
Requires-Dist: scikit-learn ==1.3.0
Requires-Dist: scipy ==1.12.0
